thai_nner/__init__.py
thai_nner/config.json
thai_nner/data.py
thai_nner/model.py
thai_nner/data_loader/__init__.py
thai_nner/data_loader/features_lm_input.py
thai_nner/utils/__init__.py
thai_nner/utils/conll2span.py
thai_nner/utils/correcting_labels.py
thai_nner/utils/prediction.py
thai_nner/utils/span2json.py
thai_nner/utils/unique.py
thai_nner/utils/util.py
thai_nner-0.3.dist-info/LICENSE
thai_nner-0.3.dist-info/METADATA
thai_nner-0.3.dist-info/WHEEL
thai_nner-0.3.dist-info/top_level.txt
thai_nner-0.3.dist-info/RECORD
