Metadata-Version: 2.1
Name: thai-nner
Version: 0.3
Summary: Thai Nested Named Entity Recognition
Home-page: https://github.com/vistec-AI/Thai-NNER
Author: Weerayut Buaphet
Author-email: weerayut.fame@gmail.com
License: MIT License 
Project-URL: Source, https://github.com/vistec-AI/Thai-NNER
Project-URL: Bug Reports, https://github.com/vistec-AI/Thai-NNER/issues
Keywords: Thai,NLP,natural language processing,text analytics,text processing,localization,computational linguistics,Thai language
Platform: UNKNOWN
Classifier: Development Status :: 5 - Production/Stable
Classifier: Programming Language :: Python :: 3
Classifier: Intended Audience :: Developers
Classifier: License :: OSI Approved :: MIT License
Classifier: Topic :: Scientific/Engineering :: Artificial Intelligence
Classifier: Topic :: Text Processing
Classifier: Topic :: Text Processing :: General
Classifier: Topic :: Text Processing :: Linguistic
Requires-Python: >=3.6
Requires-Dist: torch (>=1.1)
Requires-Dist: torchvision
Requires-Dist: numpy
Requires-Dist: tqdm
Requires-Dist: tensorboard (>=1.14)
Requires-Dist: transformers
Requires-Dist: pythainlp
Requires-Dist: sentencepiece
